kicost_digikey_api_v3/__init__.py
kicost_digikey_api_v3/exceptions.py
kicost_digikey_api_v3/utils.py
kicost_digikey_api_v3/certauth/__init__.py
kicost_digikey_api_v3/certauth/certauth.py
kicost_digikey_api_v3/oauth/__init__.py
kicost_digikey_api_v3/oauth/oauth2.py
kicost_digikey_api_v3/v3/__init__.py
kicost_digikey_api_v3/v3/api.py
kicost_digikey_api_v3/v3/productinformation/__init__.py
kicost_digikey_api_v3/v3/productinformation/api_client.py
kicost_digikey_api_v3/v3/productinformation/configuration.py
kicost_digikey_api_v3/v3/productinformation/rest.py
kicost_digikey_api_v3/v3/productinformation/api/__init__.py
kicost_digikey_api_v3/v3/productinformation/api/part_search_api.py
kicost_digikey_api_v3/v3/productinformation/models/__init__.py
kicost_digikey_api_v3/v3/productinformation/models/api_error_response.py
kicost_digikey_api_v3/v3/productinformation/models/api_validation_error.py
kicost_digikey_api_v3/v3/productinformation/models/associated_product.py
kicost_digikey_api_v3/v3/productinformation/models/basic_product.py
kicost_digikey_api_v3/v3/productinformation/models/digi_reel_pricing.py
kicost_digikey_api_v3/v3/productinformation/models/filters.py
kicost_digikey_api_v3/v3/productinformation/models/iso_search_locale.py
kicost_digikey_api_v3/v3/productinformation/models/keyword_search_request.py
kicost_digikey_api_v3/v3/productinformation/models/keyword_search_response.py
kicost_digikey_api_v3/v3/productinformation/models/kit_part.py
kicost_digikey_api_v3/v3/productinformation/models/limited_parameter.py
kicost_digikey_api_v3/v3/productinformation/models/limited_taxonomy.py
kicost_digikey_api_v3/v3/productinformation/models/manufacturer_product_details_request.py
kicost_digikey_api_v3/v3/productinformation/models/media_links.py
kicost_digikey_api_v3/v3/productinformation/models/parametric_filter.py
kicost_digikey_api_v3/v3/productinformation/models/pid_vid.py
kicost_digikey_api_v3/v3/productinformation/models/price_break.py
kicost_digikey_api_v3-0.1.3.dist-info/LICENSE
kicost_digikey_api_v3-0.1.3.dist-info/METADATA
kicost_digikey_api_v3-0.1.3.dist-info/WHEEL
kicost_digikey_api_v3-0.1.3.dist-info/top_level.txt
kicost_digikey_api_v3-0.1.3.dist-info/RECORD
