Metadata-Version: 2.1
Name: kicost-digikey-api-v3
Version: 0.1.3
Summary: KiCost plugin for the Digikey PartSearch API
Home-page: https://github.com/set-soft/kicost-digikey-api-v3
Author: Salvador E. Tropea
Author-email: stropea@inti.gob.ar
License: GPL v3
Platform: UNKNOWN
Classifier: Development Status :: 3 - Alpha
Classifier: Environment :: Web Environment
Classifier: Intended Audience :: Developers
Classifier: License :: OSI Approved :: GNU General Public License v3 (GPLv3)
Classifier: Programming Language :: Python :: 2.7
Classifier: Programming Language :: Python :: 3.6
Classifier: Topic :: Software Development
Requires-Dist: certifi
Requires-Dist: inflection (>=0.3.1)
Requires-Dist: pyopenssl
Requires-Dist: python-dateutil
Requires-Dist: requests (>=2.21)
Requires-Dist: setuptools
Requires-Dist: six
Requires-Dist: tldextract
Requires-Dist: urllib3 (>=1.24)
